README.md
setup.cfg
setup.py
TOPSIS_Snehal_101803036/TOPSIS.py
TOPSIS_Snehal_101803036/__init__.py
TOPSIS_Snehal_101803036.egg-info/PKG-INFO
TOPSIS_Snehal_101803036.egg-info/SOURCES.txt
TOPSIS_Snehal_101803036.egg-info/dependency_links.txt
TOPSIS_Snehal_101803036.egg-info/requires.txt
TOPSIS_Snehal_101803036.egg-info/top_level.txt